{
    "created_time": "2025-10-05T01:52:49Z",
    "files": [
        {
            "attachment_folder": "",
            "created_time": "2025-10-05T05:06:46Z",
            "id": "987",
            "modified_time": "2025-10-05T05:06:46Z",
            "name": "关闭右键菜单搜索.png",
            "signature": "425087427739253990",
            "tags": [
            ]
        },
        {
            "attachment_folder": "",
            "created_time": "2025-10-05T05:06:46Z",
            "id": "988",
            "modified_time": "2025-10-05T05:06:46Z",
            "name": "关闭自动索引.png",
            "signature": "1504874057431121126",
            "tags": [
            ]
        },
        {
            "attachment_folder": "",
            "created_time": "2025-10-05T05:06:46Z",
            "id": "989",
            "modified_time": "2025-10-05T05:06:46Z",
            "name": "搜索前立即更新索引.png",
            "signature": "13448092391414299878",
            "tags": [
            ]
        }
    ],
    "folders": [
    ],
    "id": "748",
    "modified_time": "2025-10-05T01:52:49Z",
    "signature": "3450525728924356465",
    "version": 3
}
