{
    "created_time": "2025-10-05T08:26:43Z",
    "files": [
        {
            "attachment_folder": "",
            "created_time": "2025-10-05T08:26:44Z",
            "id": "4515",
            "modified_time": "2025-10-05T08:26:44Z",
            "name": "Windows Terminal.md",
            "signature": "33806398016072644",
            "tags": [
            ]
        }
    ],
    "folders": [
        {
            "name": "Download Manager"
        },
        {
            "name": "File Archiver"
        },
        {
            "name": "File Editing"
        },
        {
            "name": "File Search"
        },
        {
            "name": "File Sharing"
        },
        {
            "name": "Multimedia"
        },
        {
            "name": "Package Manager"
        },
        {
            "name": "Password Manager"
        }
    ],
    "id": "4473",
    "modified_time": "2025-10-05T08:26:43Z",
    "signature": "2906278399572061123",
    "version": 3
}
