{
    "created_time": "2025-10-05T01:52:43Z",
    "files": [
        {
            "attachment_folder": "",
            "created_time": "2025-10-05T01:52:43Z",
            "id": "12",
            "modified_time": "2025-10-05T01:52:43Z",
            "name": "VeraCrypt.md",
            "signature": "12951684624007941995",
            "tags": [
            ]
        }
    ],
    "folders": [
    ],
    "id": "11",
    "modified_time": "2025-10-05T01:52:43Z",
    "signature": "16291522769007529835",
    "version": 3
}
