{
    "created_time": "2025-10-13T02:06:45Z",
    "files": [
        {
            "attachment_folder": "",
            "created_time": "2025-10-13T02:06:45Z",
            "id": "8314",
            "modified_time": "2025-10-13T02:06:45Z",
            "name": "Goldendict.md",
            "signature": "3628286067300130485",
            "tags": [
            ]
        },
        {
            "attachment_folder": "",
            "created_time": "2025-10-14T02:06:22Z",
            "id": "8516",
            "modified_time": "2025-10-14T02:06:22Z",
            "name": "Goldendict.md",
            "signature": "4541422622967967774",
            "tags": [
            ]
        }
    ],
    "folders": [
    ],
    "id": "8252",
    "modified_time": "2025-10-13T02:06:45Z",
    "signature": "6442724341903548085",
    "version": 3
}
